{"trackers":["work","life"],"tracker_info":{"work":{"id":"work","title":"Work","description":"","projects":["OBk33wgwqh","TUHUQYwXKD"],"project_info":{"OBk33wgwqh":{"id":"OBk33wgwqh","title":"Core Innovation Days","notes":{},"tasks":["0dQzDgeFNT","WUKJ02MVMr","dlzpsAZOtL"],"task_info":{"0dQzDgeFNT":{"id":"0dQzDgeFNT","title":"Benchmark","status":"new","assignees":["Gurpreet Singh"],"notes":{"ops":[{"insert":"Change pushing code for fixed cardinality\nTest throughput for ADS IPL pusher\nBenchmark E2E latency without any tunings\nBenchmark E2E latency with expedite + smaller QT rate\nTest slicer for MS\nTo try: QT rate, expedite, partitioning, #MS replicas, MS flush rate\nRemove rounding altogether for MRT (read freshest data possible) - this bypasses all caches\n"}]},"action_items":[],"action_item_info":{}},"WUKJ02MVMr":{"id":"WUKJ02MVMr","title":"Debug reading from PRDs","status":"new","assignees":["Bin Lyu"],"notes":{"ops":[{"insert":"\n"}]},"action_items":[],"action_item_info":{}},"dlzpsAZOtL":{"id":"dlzpsAZOtL","title":"Untitled task","status":"new","assignees":[],"notes":{},"action_items":[],"action_item_info":{}}}},"TUHUQYwXKD":{"id":"TUHUQYwXKD","title":"Auto-tuning Delta Policy for Efficient Compaction","notes":{},"tasks":["6Kz7Y86ddq"],"task_info":{"6Kz7Y86ddq":{"id":"6Kz7Y86ddq","title":"Build proposal","status":"new","assignees":["Gurpreet Singh"],"notes":{},"action_items":[],"action_item_info":{}}}}}},"life":{"id":"life","title":"Six Pillars of Life","description":"Staying happy is the goal ...","projects":["f8ja9ed1kc","klLh9RwPzw","GyYKb3K1Vl","P6EA7LUt1Y","vRsS2u4pAe"],"project_info":{"f8ja9ed1kc":{"id":"f8ja9ed1kc","title":"Health & Mindfulness","notes":{},"tasks":["w9lfzD14IW","EzBZe5BuC6","S3NiKGJbha","K1b07bVHUI","fWELXr8VwU","6NfjgF0ixi"],"task_info":{"w9lfzD14IW":{"id":"w9lfzD14IW","title":"Exercise for 1 hour every day","status":"new","assignees":[],"notes":{"ops":[{"insert":"\n"}]},"action_items":[],"action_item_info":{}},"EzBZe5BuC6":{"id":"EzBZe5BuC6","title":"Cook at least twice a week","status":"new","assignees":[],"notes":{},"action_items":[],"action_item_info":{}},"S3NiKGJbha":{"id":"S3NiKGJbha","title":"Add more fruits & veggies to your diet","status":"new","assignees":[],"notes":{},"action_items":[],"action_item_info":{}},"K1b07bVHUI":{"id":"K1b07bVHUI","title":"Meditate for 5 minutes every day","status":"new","assignees":[],"notes":{},"action_items":[],"action_item_info":{}},"fWELXr8VwU":{"id":"fWELXr8VwU","title":"Improve focus","status":"new","assignees":[],"notes":{},"action_items":[],"action_item_info":{}},"6NfjgF0ixi":{"id":"6NfjgF0ixi","title":"Work towards fixing physical injuries","status":"in_progress","assignees":["Gurpreet Singh"],"notes":{},"action_items":[],"action_item_info":{}}}},"klLh9RwPzw":{"id":"klLh9RwPzw","title":"Stability","notes":{},"tasks":["6UROcaJlhX","kHkKj9HlDU","GM4QclF4YD"],"task_info":{"6UROcaJlhX":{"id":"6UROcaJlhX","title":"Apply for NIW","status":"new","assignees":[],"notes":{"ops":[{"insert":"\n"}]},"action_items":[],"action_item_info":{}},"kHkKj9HlDU":{"id":"kHkKj9HlDU","title":"Work towards EB1","status":"new","assignees":[],"notes":{},"action_items":[],"action_item_info":{}},"GM4QclF4YD":{"id":"GM4QclF4YD","title":"Find long-term goals and develop strategies to achieve them","status":"new","assignees":[],"notes":{},"action_items":[],"action_item_info":{}}}},"GyYKb3K1Vl":{"id":"GyYKb3K1Vl","title":"Love & Social","notes":{},"tasks":["hyH0sb9nRR","Gd8Ukc35cH","ZA8sNYaZDe","bLVBwEnQV8","XKWkdNE2Ow"],"task_info":{"hyH0sb9nRR":{"id":"hyH0sb9nRR","title":"Improve sexual health","status":"new","assignees":[],"notes":{},"action_items":[],"action_item_info":{}},"Gd8Ukc35cH":{"id":"Gd8Ukc35cH","title":"Check up on Nanu","status":"new","assignees":[],"notes":{},"action_items":[],"action_item_info":{}},"ZA8sNYaZDe":{"id":"ZA8sNYaZDe","title":"Remain in touch with old friends","status":"new","assignees":[],"notes":{},"action_items":[],"action_item_info":{}},"bLVBwEnQV8":{"id":"bLVBwEnQV8","title":"Have at least 2 meals with people every week","status":"new","assignees":[],"notes":{},"action_items":[],"action_item_info":{}},"XKWkdNE2Ow":{"id":"XKWkdNE2Ow","title":"Develop deeper relations with people around you","status":"new","assignees":[],"notes":{},"action_items":[],"action_item_info":{}}}},"P6EA7LUt1Y":{"id":"P6EA7LUt1Y","title":"Finance","notes":{},"tasks":["zVEBQXHRqA","QtRAouTLWg"],"task_info":{"zVEBQXHRqA":{"id":"zVEBQXHRqA","title":"Improve your portfolio","status":"new","assignees":[],"notes":{},"action_items":["sxZJdIXUSe"],"action_item_info":{"sxZJdIXUSe":{"id":"sxZJdIXUSe","title":"Move money into Betterment","status":"new"}}},"QtRAouTLWg":{"id":"QtRAouTLWg","title":"Set-up monthly budgeting","status":"new","assignees":[],"notes":{},"action_items":[],"action_item_info":{}}}},"vRsS2u4pAe":{"id":"vRsS2u4pAe","title":"Play","notes":{},"tasks":["EIHxVWrfvQ","qqaqGOhNhn","qjN7CTf42o","867zZCJaLJ"],"task_info":{"EIHxVWrfvQ":{"id":"EIHxVWrfvQ","title":"Create travel itineraries for 2025","status":"new","assignees":[],"notes":{},"action_items":[],"action_item_info":{}},"qqaqGOhNhn":{"id":"qqaqGOhNhn","title":"Create list of National Parks to visit in 2025","status":"new","assignees":[],"notes":{},"action_items":[],"action_item_info":{}},"qjN7CTf42o":{"id":"qjN7CTf42o","title":"Build a hobby","status":"new","assignees":[],"notes":{},"action_items":[],"action_item_info":{}},"867zZCJaLJ":{"id":"867zZCJaLJ","title":"6 Month Learnings","status":"new","assignees":[],"notes":{},"action_items":["9miieGOdvu","pOjOii1hHl","ZCHbZVRFlz","b22Vw96VbX","XjPusBGRet","ZgLzQzSeOG","GoNYF71oNu","6rJ3U79eMv","clEIgHlFD8","tFahgpBtRj","eYtpiiKSwV","LrR3mNRVlp","ppu3vfaxe7","vyEVTk1P2t"],"action_item_info":{"9miieGOdvu":{"id":"9miieGOdvu","title":"DSLR","status":"new"},"pOjOii1hHl":{"id":"pOjOii1hHl","title":"Motorbike","status":"new"},"ZCHbZVRFlz":{"id":"ZCHbZVRFlz","title":"Ceramics","status":"new"},"b22Vw96VbX":{"id":"b22Vw96VbX","title":"Bartending","status":"new"},"XjPusBGRet":{"id":"XjPusBGRet","title":"Interior Designing","status":"new"},"ZgLzQzSeOG":{"id":"ZgLzQzSeOG","title":"Vegan cooking","status":"new"},"GoNYF71oNu":{"id":"GoNYF71oNu","title":"Vegan Baking","status":"new"},"6rJ3U79eMv":{"id":"6rJ3U79eMv","title":"Keto Baking","status":"new"},"clEIgHlFD8":{"id":"clEIgHlFD8","title":"Sewing","status":"new"},"tFahgpBtRj":{"id":"tFahgpBtRj","title":"Painting","status":"new"},"eYtpiiKSwV":{"id":"eYtpiiKSwV","title":"Portrait drawing","status":"new"},"LrR3mNRVlp":{"id":"LrR3mNRVlp","title":"Woodworking","status":"new"},"ppu3vfaxe7":{"id":"ppu3vfaxe7","title":"DJing","status":"new"},"vyEVTk1P2t":{"id":"vyEVTk1P2t","title":"Handyman stuff","status":"new"}}}}}}}}}